ptttl/__init__.py
ptttl/__main__.py
ptttl/audio.py
ptttl/parser.py
ptttl-1.2.0.dist-info/LICENSE
ptttl-1.2.0.dist-info/METADATA
ptttl-1.2.0.dist-info/WHEEL
ptttl-1.2.0.dist-info/top_level.txt
ptttl-1.2.0.dist-info/RECORD
