Metadata-Version: 2.1
Name: ptttl
Version: 1.2.0
Summary: Parses PTTTL/RTTTL musical notation files
Home-page: http://github.com/eriknyquist/ptttl
Author: Erik Nyquist
Author-email: eknyquist@gmail.com
License: Apache 2.0
Platform: UNKNOWN
Classifier: License :: OSI Approved :: Apache Software License
Classifier: Operating System :: OS Independent
Classifier: Programming Language :: Python
Classifier: Natural Language :: English
Classifier: Intended Audience :: Developers
Classifier: Intended Audience :: Science/Research
Classifier: Intended Audience :: Education
Classifier: Intended Audience :: Information Technology
Classifier: Programming Language :: Python :: 2
Classifier: Programming Language :: Python :: 2.7
Requires-Dist: tones (==1.2.0)
